spotifython/__init__.py
spotifython/abc.py
spotifython/album.py
spotifython/artist.py
spotifython/authentication.py
spotifython/cache.py
spotifython/client.py
spotifython/connection.py
spotifython/datatypes.py
spotifython/episode.py
spotifython/errors.py
spotifython/me.py
spotifython/playlist.py
spotifython/scope.py
spotifython/show.py
spotifython/track.py
spotifython/uri.py
spotifython/user.py
spotifython-0.2.11.dist-info/LICENSE
spotifython-0.2.11.dist-info/METADATA
spotifython-0.2.11.dist-info/WHEEL
spotifython-0.2.11.dist-info/top_level.txt
spotifython-0.2.11.dist-info/RECORD
