Metadata-Version: 2.1
Name: spotifython
Version: 0.2.11
Summary: A caching python interface to readonly parts of the spotify api.
Home-page: https://github.com/vawvaw/spotifython
Author: VAWVAW
Author-email: vawvaw@vaw-valentin.de
License: GPLv3
Project-URL: Bug Tracker, https://github.com/vawvaw/spotifython/issues
Project-URL: Documentation, https://spotifython.readthedocs.io/
Classifier: Development Status :: 4 - Beta
Classifier: Intended Audience :: Developers
Classifier: Programming Language :: Python :: 3.10
Classifier: License :: OSI Approved :: GNU General Public License v3 (GPLv3)
Classifier: Natural Language :: English
Classifier: Operating System :: OS Independent
Classifier: Topic :: Internet
Classifier: Topic :: Software Development :: Libraries
Classifier: Topic :: Software Development :: Libraries :: Python Modules
Classifier: Topic :: Utilities
Classifier: Typing :: Typed
Requires-Python: >=3.10
License-File: LICENSE
Requires-Dist: requests
